[
    {
        "question": "What is the admission process?",
        "answer": "Admission process includes online application, document verification and fee payment."
    },
    {
        "question": "What is BCA fee structure?",
        "answer": "BCA fee is \u20b945,000 per year."
    },
    {
        "question": "What courses are offered?",
        "answer": "We offer BCA, BBA, BCom, BTech, MBA and MCom."
    },
    {
        "question": "Is hostel facility available?",
        "answer": "Yes, hostel facility is available for both boys and girls."
    },
    {
        "question": "What is B.Tech fee structure?",
        "answer": "B.Tech fee structure is 100000 per year"
    }
]